pseudo_sampler/__init__.py
pseudo_sampler/data_handling.py
pseudo_sampler/eps.py
pseudo_sampler/regressor.py
pseudo_sampler/vae_regressor.py
pseudo_sampler_roohy-0.1.1.dist-info/LICENSE
pseudo_sampler_roohy-0.1.1.dist-info/METADATA
pseudo_sampler_roohy-0.1.1.dist-info/WHEEL
pseudo_sampler_roohy-0.1.1.dist-info/top_level.txt
pseudo_sampler_roohy-0.1.1.dist-info/RECORD
